sqlany_django/client.py
sqlany_django/validation.py
sqlany_django/creation.py
sqlany_django/compiler.py
sqlany_django/schema.py
sqlany_django/introspection.py
sqlany_django/base.py
sqlany_django/__init__.py
sqlany_django-1.13.dist-info/top_level.txt
sqlany_django-1.13.dist-info/METADATA
sqlany_django-1.13.dist-info/DESCRIPTION.rst
sqlany_django-1.13.dist-info/metadata.json
sqlany_django-1.13.dist-info/WHEEL
sqlany_django-1.13.dist-info/RECORD
